techupdate_extractor/__init__.py
techupdate_extractor/main.py
techupdate_extractor/prompts.py
techupdate_extractor-2025.12.21083811.dist-info/METADATA
techupdate_extractor-2025.12.21083811.dist-info/WHEEL
techupdate_extractor-2025.12.21083811.dist-info/top_level.txt
techupdate_extractor-2025.12.21083811.dist-info/RECORD
